{
	"name": "pipeline8",
	"properties": {
		"activities": [
			{
				"name": "Get Metadata_item",
				"type": "GetMetadata",
				"dependsOn": [],
				"policy": {
					"timeout": "0.12:00:00",
					"retry": 0,
					"retryIntervalInSeconds": 30,
					"secureOutput": false,
					"secureInput": false
				},
				"userProperties": [],
				"typeProperties": {
					"dataset": {
						"referenceName": "Emp_dataset",
						"type": "DatasetReference"
					},
					"fieldList": [
						"structure"
					],
					"storeSettings": {
						"type": "AzureBlobStorageReadSettings",
						"enablePartitionDiscovery": false
					},
					"formatSettings": {
						"type": "DelimitedTextReadSettings"
					}
				}
			},
			{
				"name": "ForEach1",
				"type": "ForEach",
				"dependsOn": [
					{
						"activity": "Get Metadata_item",
						"dependencyConditions": [
							"Completed"
						]
					}
				],
				"userProperties": [],
				"typeProperties": {
					"items": {
						"value": "@activity('Get Metadata_item').output.structure",
						"type": "Expression"
					},
					"isSequential": false,
					"activities": [
						{
							"name": "Copy data1",
							"type": "Copy",
							"dependsOn": [],
							"policy": {
								"timeout": "0.12:00:00",
								"retry": 0,
								"retryIntervalInSeconds": 30,
								"secureOutput": false,
								"secureInput": false
							},
							"userProperties": [],
							"typeProperties": {
								"source": {
									"type": "DelimitedTextSource",
									"storeSettings": {
										"type": "AzureBlobStorageReadSettings",
										"recursive": true,
										"wildcardFileName": {
											"value": "@split(item().name,',')[0]",
											"type": "Expression"
										},
										"enablePartitionDiscovery": false
									},
									"formatSettings": {
										"type": "DelimitedTextReadSettings"
									}
								},
								"sink": {
									"type": "DelimitedTextSink",
									"storeSettings": {
										"type": "AzureBlobStorageWriteSettings"
									},
									"formatSettings": {
										"type": "DelimitedTextWriteSettings",
										"quoteAllText": true,
										"fileExtension": ".txt"
									}
								},
								"enableStaging": false,
								"translator": {
									"type": "TabularTranslator",
									"typeConversion": true,
									"typeConversionSettings": {
										"allowDataTruncation": true,
										"treatBooleanAsNumber": false
									}
								}
							},
							"inputs": [
								{
									"referenceName": "Emp_dataset",
									"type": "DatasetReference"
								}
							],
							"outputs": [
								{
									"referenceName": "DelimitedText3",
									"type": "DatasetReference"
								}
							]
						}
					]
				}
			}
		],
		"concurrency": 1,
		"variables": {
			"Item_name": {
				"type": "String"
			},
			"last_modified": {
				"type": "String"
			},
			"start_time": {
				"type": "String"
			}
		},
		"annotations": []
	}
}